pyrainbird/__init__.py
pyrainbird/client.py
pyrainbird/data.py
pyrainbird/encryption.py
pyrainbird/rainbird.py
pyrainbird/resources/__init__.py
pyrainbird/resources/models.yaml
pyrainbird/resources/sipcommands.yaml
pyrainbird_alternative-0.5.4.dist-info/LICENSE
pyrainbird_alternative-0.5.4.dist-info/LICENSE.txt
pyrainbird_alternative-0.5.4.dist-info/METADATA
pyrainbird_alternative-0.5.4.dist-info/WHEEL
pyrainbird_alternative-0.5.4.dist-info/top_level.txt
pyrainbird_alternative-0.5.4.dist-info/zip-safe
pyrainbird_alternative-0.5.4.dist-info/RECORD
